{"segments":[{"x":311,"y":211,"segment":0},{"x":311,"y":211,"segment":1},{"x":311,"y":211,"segment":0},{"x":309,"y":207,"segment":1},{"x":306,"y":203,"segment":2},{"x":303,"y":200,"segment":3},{"x":301,"y":196,"segment":4},{"x":298,"y":192,"segment":5},{"x":295,"y":188,"segment":6},{"x":292,"y":185,"segment":7},{"x":289,"y":181,"segment":8},{"x":286,"y":178,"segment":9},{"x":283,"y":174,"segment":0},{"x":280,"y":171,"segment":1},{"x":277,"y":167,"segment":2},{"x":274,"y":164,"segment":3},{"x":271,"y":161,"segment":4},{"x":268,"y":157,"segment":5},{"x":265,"y":154,"segment":6},{"x":261,"y":150,"segment":7},{"x":258,"y":147,"segment":8},{"x":255,"y":144,"segment":9},{"x":251,"y":141,"segment":0},{"x":245,"y":135,"segment":1},{"x":238,"y":129,"segment":2},{"x":232,"y":123,"segment":3},{"x":225,"y":118,"segment":4},{"x":218,"y":112,"segment":5},{"x":211,"y":107,"segment":6},{"x":204,"y":102,"segment":7},{"x":196,"y":98,"segment":8},{"x":189,"y":93,"segment":9},{"x":181,"y":89,"segment":0},{"x":194,"y":94,"segment":1},{"x":208,"y":100,"segment":2},{"x":222,"y":107,"segment":3},{"x":235,"y":115,"segment":4},{"x":248,"y":124,"segment":5},{"x":258,"y":131,"segment":6},{"x":268,"y":138,"segment":7},{"x":275,"y":144,"segment":8},{"x":279,"y":148,"segment":9},{"x":281,"y":149,"segment":0},{"x":281,"y":136,"segment":1},{"x":280,"y":124,"segment":2},{"x":279,"y":113,"segment":3},{"x":276,"y":102,"segment":4},{"x":273,"y":92,"segment":5},{"x":268,"y":82,"segment":6},{"x":262,"y":74,"segment":7},{"x":255,"y":66,"segment":8},{"x":246,"y":58,"segment":9},{"x":236,"y":52,"segment":0},{"x":225,"y":47,"segment":1},{"x":214,"y":42,"segment":2},{"x":204,"y":38,"segment":3},{"x":193,"y":36,"segment":4},{"x":182,"y":33,"segment":5},{"x":171,"y":32,"segment":6},{"x":159,"y":31,"segment":7},{"x":148,"y":30,"segment":8},{"x":136,"y":29,"segment":9},{"x":124,"y":29,"segment":0},{"x":116,"y":28,"segment":1},{"x":108,"y":28,"segment":2},{"x":101,"y":26,"segment":3},{"x":95,"y":25,"segment":4},{"x":90,"y":24,"segment":5},{"x":85,"y":22,"segment":6},{"x":81,"y":21,"segment":7},{"x":78,"y":20,"segment":8},{"x":77,"y":19,"segment":9},{"x":76,"y":19,"segment":0},{"x":78,"y":30,"segment":1},{"x":81,"y":43,"segment":2},{"x":84,"y":57,"segment":3},{"x":88,"y":72,"segment":4},{"x":94,"y":88,"segment":5},{"x":100,"y":103,"segment":6},{"x":108,"y":119,"segment":7},{"x":117,"y":133,"segment":8},{"x":129,"y":146,"segment":9},{"x":142,"y":158,"segment":0},{"x":157,"y":168,"segment":1},{"x":172,"y":174,"segment":2},{"x":188,"y":179,"segment":3},{"x":203,"y":181,"segment":4},{"x":217,"y":182,"segment":5},{"x":230,"y":182,"segment":6},{"x":241,"y":181,"segment":7},{"x":250,"y":179,"segment":8},{"x":257,"y":178,"segment":9},{"x":261,"y":177,"segment":0},{"x":262,"y":178,"segment":1},{"x":262,"y":179,"segment":2},{"x":263,"y":180,"segment":3},{"x":263,"y":181,"segment":4},{"x":264,"y":182,"segment":5},{"x":265,"y":182,"segment":6},{"x":265,"y":183,"segment":7},{"x":266,"y":184,"segment":8},{"x":266,"y":185,"segment":9},{"x":267,"y":186,"segment":0},{"x":269,"y":190,"segment":1},{"x":272,"y":194,"segment":2},{"x":274,"y":198,"segment":3},{"x":276,"y":201,"segment":4},{"x":278,"y":205,"segment":5},{"x":281,"y":209,"segment":6},{"x":283,"y":213,"segment":7},{"x":285,"y":217,"segment":8},{"x":287,"y":221,"segment":9},{"x":289,"y":225,"segment":0},{"x":289,"y":225,"segment":1},{"x":289,"y":225,"segment":2},{"x":289,"y":225,"segment":3},{"x":289,"y":225,"segment":4},{"x":290,"y":226,"segment":5},{"x":290,"y":226,"segment":6},{"x":290,"y":226,"segment":7},{"x":290,"y":226,"segment":8},{"x":290,"y":226,"segment":9},{"x":290,"y":226,"segment":0},{"x":291,"y":228,"segment":1},{"x":293,"y":229,"segment":2},{"x":295,"y":230,"segment":3},{"x":296,"y":231,"segment":4},{"x":298,"y":231,"segment":5},{"x":300,"y":231,"segment":6},{"x":302,"y":231,"segment":7},{"x":304,"y":231,"segment":8},{"x":306,"y":230,"segment":9},{"x":308,"y":229,"segment":0},{"x":308,"y":229,"segment":1},{"x":308,"y":229,"segment":2},{"x":309,"y":229,"segment":3},{"x":309,"y":229,"segment":4},{"x":309,"y":229,"segment":5},{"x":309,"y":229,"segment":6},{"x":309,"y":229,"segment":7},{"x":309,"y":229,"segment":8},{"x":309,"y":229,"segment":9},{"x":309,"y":229,"segment":0},{"x":310,"y":227,"segment":1},{"x":312,"y":226,"segment":2},{"x":312,"y":224,"segment":3},{"x":313,"y":222,"segment":4},{"x":313,"y":220,"segment":5},{"x":313,"y":218,"segment":6},{"x":313,"y":217,"segment":7},{"x":313,"y":215,"segment":8},{"x":312,"y":213,"segment":9}],"meta":{"name":"Leaf","difficulty":"Easy"}}